jupyterlab_slash_copy_path/__init__.py
jupyterlab_slash_copy_path/_version.py
jupyterlab_slash_copy_path/labextension/build_log.json
jupyterlab_slash_copy_path/labextension/package.json
jupyterlab_slash_copy_path/labextension/schemas/@epi2melabs/jupyterlab-slash-copy-path/package.json.orig
jupyterlab_slash_copy_path/labextension/schemas/@epi2melabs/jupyterlab-slash-copy-path/plugin.json
jupyterlab_slash_copy_path/labextension/static/lib_index_js.7c9f7a329bffcb96bf00.js
jupyterlab_slash_copy_path/labextension/static/lib_index_js.7c9f7a329bffcb96bf00.js.map
jupyterlab_slash_copy_path/labextension/static/remoteEntry.c2f2a4b7a9a9aeb3ab62.js
jupyterlab_slash_copy_path/labextension/static/remoteEntry.c2f2a4b7a9a9aeb3ab62.js.map
jupyterlab_slash_copy_path/labextension/static/style.js
jupyterlab_slash_copy_path/labextension/static/style_index_js.9b68c02cd847b0307bbc.js
jupyterlab_slash_copy_path/labextension/static/style_index_js.9b68c02cd847b0307bbc.js.map
jupyterlab_slash_copy_path/labextension/static/vendors-node_modules_css-loader_dist_runtime_api_js-node_modules_css-loader_dist_runtime_cssW-926fd9.6a6f3ecbd40af47e5d9c.js
jupyterlab_slash_copy_path/labextension/static/vendors-node_modules_css-loader_dist_runtime_api_js-node_modules_css-loader_dist_runtime_cssW-926fd9.6a6f3ecbd40af47e5d9c.js.map
jupyterlab_slash_copy_path-0.1.0.data/data/share/jupyter/labextensions/@epi2melabs/jupyterlab-slash-copy-path/build_log.json
jupyterlab_slash_copy_path-0.1.0.data/data/share/jupyter/labextensions/@epi2melabs/jupyterlab-slash-copy-path/install.json
jupyterlab_slash_copy_path-0.1.0.data/data/share/jupyter/labextensions/@epi2melabs/jupyterlab-slash-copy-path/package.json
jupyterlab_slash_copy_path-0.1.0.data/data/share/jupyter/labextensions/@epi2melabs/jupyterlab-slash-copy-path/schemas/@epi2melabs/jupyterlab-slash-copy-path/package.json.orig
jupyterlab_slash_copy_path-0.1.0.dist-info/LICENSE
jupyterlab_slash_copy_path-0.1.0.dist-info/METADATA
jupyterlab_slash_copy_path-0.1.0.dist-info/WHEEL
jupyterlab_slash_copy_path-0.1.0.dist-info/top_level.txt
jupyterlab_slash_copy_path-0.1.0.dist-info/RECORD
