Metadata-Version: 2.1
Name: jupyterlab-slash-copy-path
Version: 0.1.0
Summary: Change the prefix attached to context menu copied links
Home-page: https://github.com/epi2me-labs/jupyterlab-slash-copy-path
Author: epi2melabs
Author-email: epi2melabs@nanoporetech.com
License: BSD-3-Clause
Keywords: Jupyter,JupyterLab,JupyterLab3
Platform: Linux
Platform: Mac OS X
Platform: Windows
Classifier: License :: OSI Approved :: BSD License
Classifier: Programming Language :: Python
Classifier: Programming Language :: Python :: 3
Classifier: Programming Language :: Python :: 3.6
Classifier: Programming Language :: Python :: 3.7
Classifier: Programming Language :: Python :: 3.8
Classifier: Programming Language :: Python :: 3.9
Classifier: Framework :: Jupyter
Requires-Python: >=3.6
Requires-Dist: jupyter-server (<2,>=1.6)
